dephix/api_models/__init__.py
dephix/api_models/interfaces/__init__.py
dephix/api_models/interfaces/market_http_client.py
dephix/api_models/interfaces/market_ws_client.py
dephix/api_models/models/__init__.py
dephix/api_models/models/funding_rate.py
dephix/api_models/models/instruments_info.py
dephix/api_models/models/kline_candle.py
dephix/api_models/models/lot_size_filter.py
dephix/api_models/models/place_order_result.py
dephix_api_models-0.1.7.dist-info/licenses/LICENSE
dephix_api_models-0.1.7.dist-info/METADATA
dephix_api_models-0.1.7.dist-info/WHEEL
dephix_api_models-0.1.7.dist-info/top_level.txt
dephix_api_models-0.1.7.dist-info/RECORD
